sidserver/__init__.py
sidserver/client.py
sidserver/lib/__init__.py
sidserver/lib/util/__init__.py
sidserver/lib/util/device.py
sidserver/lib/util/headers.py
sidserver/lib/util/helpers.py
sidserver-2.6.dist-info/METADATA
sidserver-2.6.dist-info/WHEEL
sidserver-2.6.dist-info/top_level.txt
sidserver-2.6.dist-info/RECORD
