Metadata-Version: 2.1
Name: sidserver
Version: 2.6
Summary: for coin gen
Home-page: 
Author: .....
Author-email: ptimer60@gmail.com
License: ...
Keywords: aminoapps,sidserver,amino,amino-bot,narvii,api,python,python3,python3.x
Requires-Python: >=3.6
Requires-Dist: platforn-socket
Requires-Dist: setuptools
Requires-Dist: json-minify
Requires-Dist: six
Requires-Dist: websockets
